{
  "results": [
    {
      "action": "search_replace",
      "id": "cc-body-text",
      "timestamp": "2026-05-29T17:47:16.456313",
      "result": {
        "success": true,
        "data": {
          "search": "Our college catalysts are BMIIL",
          "replace": "Our campus catalysts are BMIIL",
          "dry_run": false,
          "affected": [
            {
              "post_id": "1117",
              "title": "Team",
              "count": 1
            }
          ],
          "count": 1,
          "message": "1 updated."
        }
      }
    },
    {
      "action": "search_replace",
      "id": "cc-lower",
      "timestamp": "2026-05-29T17:47:17.561848",
      "result": {
        "success": true,
        "data": {
          "search": "college catalysts are BMIIL",
          "replace": "campus catalysts are BMIIL",
          "dry_run": false,
          "affected": [],
          "count": 0,
          "message": "0 updated."
        }
      }
    }
  ],
  "last_run": "2026-05-29T17:47:18.380776",
  "status": "completed",
  "commands_run": 2
}